{
  "first-name": "Łukasz",
  "sur-name": "Kusek",
  "contact": {
    "phone": "(44) 777 420 1310",
    "email": "lukasz-cv@kusek.info",
    "github": "https://github.com/lukasz-kusek",
    "linkedin": "http://pl.linkedin.com/pub/%C5%82ukasz-kusek/51/b4a/1b9/en",
    "website": "http://lukasz.kusek.info",
    "address": "Harpenden, UK"
  },
  "summary": {
    "title": "Scala Engineer (Contractor)",
    "description": "Senior software engineer with almost 6 years commercial experience (10 years including part-time jobs). My area of expertise is building highly available backend services on JVM platform (Scala - 10 months, Java - 5 years)."
  },
  "availability": "End of April / beginning of May 2016",
  "experience": [
    {
      "positions": [
        {
          "title": "Senior Software Engineer (Scala)"
        }
      ],
      "employment": "full-time",
      "company": {
        "name": "Ocado Technology",
        "industry": "Online grocery retail",
        "location": {
          "city": "Hatfield",
          "country": "United Kingdom"
        }
      },
      "projects": [
        {
          "description": "I work on low latency services (<10ms) that informs shoppers what is in and out of stock. Services are designed to be highly available and scalable (akka cluster, AWS, blue-green deployment), highly responsible (actor model) and low latency (in-memory cache with akka sharding). Services are based on CQRS and event sourcing."
        },
        {
          "description": "Introduced idea of team goal which helped us prioritize tasks and have common vision of our services."
        },
        {
          "description": "Proposed adjustments to our sprint (pair programming, one story at a time) that improved collaboration and helped building trust."
        },
        {
          "description": "Created two OAuth2 libraries (non-blocking client with caching capabilities and testing library) that are widely used across teams at Ocado Technology. Libraries are shared as internal open source projects."
        },
        {
          "description": "Configured Continuous Delivery pipelines. Did a research on implementation of BlueGreen Deployment and found major flaws in the early stage what allowed us to prepare architecture of our applications before it's released to production."
        },
        {
          "description": "Successfully migrated production and integration tests environments to new AWS account before given deadline."
        }
      ],
      "start-date": "2015-07",
      "skills": [
        {
          "name": "Scala",
          "usage-frequency": "day-to-day",
          "category": "language"
        },
        {
          "name": "Akka",
          "usage-frequency": "day-to-day",
          "category": "library"
        },
        {
          "name": "Spray",
          "usage-frequency": "often",
          "category": "library"
        },
        {
          "name": "AWS",
          "usage-frequency": "often",
          "category": "tool"
        },
        {
          "name": "Git",
          "usage-frequency": "day-to-day",
          "category": "tool"
        },
        {
          "name": "Event Sourcing",
          "usage-frequency": "often",
          "category": "other"
        },
        {
          "name": "Microservices",
          "usage-frequency": "day-to-day",
          "category": "other"
        },
        {
          "name": "JSON",
          "usage-frequency": "day-to-day",
          "category": "other"
        },
        {
          "name": "REST",
          "usage-frequency": "day-to-day",
          "category": "other"
        },
        {
          "name": "Swagger",
          "usage-frequency": "occasionally",
          "category": "tool"
        },
        {
          "name": "ScalaTest",
          "usage-frequency": "day-to-day",
          "category": "library"
        },
        {
          "name": "JIRA",
          "usage-frequency": "day-to-day",
          "category": "tool"
        },
        {
          "name": "Guice",
          "usage-frequency": "day-to-day",
          "category": "library"
        },
        {
          "name": "DynamoDB",
          "usage-frequency": "occasionally",
          "category": "database"
        },
        {
          "name": "OAuth2",
          "usage-frequency": "often",
          "category": "other"
        },
        {
          "name": "Crucible",
          "usage-frequency": "often",
          "category": "tool"
        },
        {
          "name": "Kibana",
          "usage-frequency": "often",
          "category": "tool"
        },
        {
          "name": "Logstash",
          "usage-frequency": "occasionally",
          "category": "tool"
        },
        {
          "name": "GO",
          "usage-frequency": "day-to-day",
          "category": "tool"
        },
        {
          "name": "Intellij IDEA",
          "usage-frequency": "day-to-day",
          "category": "tool"
        },
        {
          "name": "Maven",
          "usage-frequency": "day-to-day",
          "category": "tool"
        }
      ]
    },
    {
      "positions": [
        {
          "title": "Senior Software Engineer (Java)"
        }
      ],
      "employment": "full-time",
      "company": {
        "name": "Ocado Technology",
        "industry": "Online grocery retail",
        "location": {
          "city": "Hatfield",
          "country": "United Kingdom"
        }
      },
      "projects": [
        {
          "description": "I've worked on replatforming existing order management services to cloud based microservices."
        },
        {
          "description": "Successfully introduced testing standards in the team (testing levels definitions - unit, component, system tests; naming convention)."
        },
        {
          "description": "Lead sessions to present importance of tests quality."
        }
      ],
      "start-date": "2015-02",
      "end-date": "2015-07",
      "skills": [
        {
          "name": "Java",
          "detailed-name": "Java 8",
          "usage-frequency": "day-to-day",
          "category": "language"
        },
        {
          "name": "AWS",
          "usage-frequency": "often",
          "category": "tool"
        },
        {
          "name": "Git",
          "usage-frequency": "day-to-day",
          "category": "tool"
        },
        {
          "name": "Microservices",
          "usage-frequency": "day-to-day",
          "category": "other"
        },
        {
          "name": "JSON",
          "usage-frequency": "day-to-day",
          "category": "other"
        },
        {
          "name": "REST",
          "usage-frequency": "day-to-day",
          "category": "other"
        },
        {
          "name": "Swagger",
          "usage-frequency": "occasionally",
          "category": "tool"
        },
        {
          "name": "Hystrix",
          "usage-frequency": "occasionally",
          "category": "library"
        },
        {
          "name": "PostgreSQL",
          "usage-frequency": "occasionally",
          "category": "database"
        },
        {
          "name": "Python",
          "usage-frequency": "occasionally",
          "category": "language"
        },
        {
          "name": "OAuth2",
          "usage-frequency": "occasionally",
          "category": "other"
        },
        {
          "name": "Cucumber",
          "usage-frequency": "often",
          "category": "library"
        },
        {
          "name": "Mockito",
          "usage-frequency": "day-to-day",
          "category": "library"
        },
        {
          "name": "AssertJ",
          "usage-frequency": "day-to-day",
          "category": "library"
        },
        {
          "name": "JUnit",
          "usage-frequency": "day-to-day",
          "category": "library"
        },
        {
          "name": "Jenkins",
          "usage-frequency": "day-to-day",
          "category": "tool"
        },
        {
          "name": "Guice",
          "usage-frequency": "day-to-day",
          "category": "library"
        },
        {
          "name": "DynamoDB",
          "usage-frequency": "occasionally",
          "category": "database"
        },
        {
          "name": "Crucible",
          "usage-frequency": "often",
          "category": "tool"
        },
        {
          "name": "Kibana",
          "usage-frequency": "often",
          "category": "tool"
        },
        {
          "name": "Logstash",
          "usage-frequency": "occasionally",
          "category": "tool"
        },
        {
          "name": "GO",
          "usage-frequency": "day-to-day",
          "category": "tool"
        },
        {
          "name": "Intellij IDEA",
          "usage-frequency": "day-to-day",
          "category": "tool"
        },
        {
          "name": "Maven",
          "usage-frequency": "day-to-day",
          "category": "tool"
        }
      ]
    },
    {
      "positions": [
        {
          "title": "Senior Software Developer (Java) - contractor"
        }
      ],
      "employment": "full-time",
      "company": {
        "name": "Luxoft",
        "industry": "Investment banking",
        "location": {
          "city": "Krakow",
          "country": "Poland"
        }
      },
      "projects": [
        {
          "description": "Contractor at UBS Investment Bank. I worked on capital commitment, automatic indication of interest generation and trade advertising applications at Cash Equities project."
        },
        {
          "description": "Introduced automatic system tests, enhanced logging that enabled tracking single requests, automatic build system using Gradle and Jenkins which improved speed and reliability of the process."
        }
      ],
      "start-date": "2014-03",
      "end-date": "2015-01",
      "skills": [
        {
          "name": "Java",
          "detailed-name": "Java 6",
          "usage-frequency": "day-to-day",
          "category": "language"
        },
        {
          "name": "QuickFIX/J",
          "usage-frequency": "often",
          "category": "library"
        },
        {
          "name": "CameronFIX",
          "usage-frequency": "day-to-day",
          "category": "library"
        },
        {
          "name": "Spock",
          "start-date": "2014-05",
          "usage-frequency": "occasionally",
          "category": "library"
        },
        {
          "name": "Groovy",
          "start-date": "2014-05",
          "usage-frequency": "occasionally",
          "category": "language"
        },
        {
          "name": "Git",
          "start-date": "2014-08",
          "usage-frequency": "day-to-day",
          "category": "tool"
        },
        {
          "name": "Gradle",
          "start-date": "2014-06",
          "usage-frequency": "often",
          "category": "tool"
        },
        {
          "name": "Jenkins",
          "start-date": "2014-10",
          "usage-frequency": "often",
          "category": "tool"
        },
        {
          "name": "Oracle",
          "usage-frequency": "occasionally",
          "category": "database"
        },
        {
          "name": "JIRA",
          "usage-frequency": "day-to-day",
          "category": "tool"
        },
        {
          "name": "SVN",
          "usage-frequency": "day-to-day",
          "category": "tool"
        },
        {
          "name": "Intellij IDEA",
          "usage-frequency": "day-to-day",
          "category": "tool"
        },
        {
          "name": "SQL",
          "usage-frequency": "occasionally",
          "category": "language"
        },
        {
          "name": "JUnit",
          "usage-frequency": "day-to-day",
          "category": "library"
        },
        {
          "name": "AssertJ",
          "usage-frequency": "day-to-day",
          "category": "library"
        },
        {
          "name": "Guava",
          "usage-frequency": "day-to-day",
          "category": "library"
        },
        {
          "name": "Mockito",
          "usage-frequency": "day-to-day",
          "category": "library"
        }
      ]
    },
    {
      "positions": [
        {
          "title": "Senior Java Developer",
          "start-date": "2013-05"
        },
        {
          "title": "Senior Java Developer - contractor",
          "start-date": "2012-05",
          "end-date": "2013-05"
        },
        {
          "title": "Java Developer - contractor",
          "end-date": "2012-04"
        }
      ],
      "employment": "full-time",
      "company": {
        "name": "Sabre",
        "industry": "Airlines and airports",
        "location": {
          "city": "Krakow",
          "country": "Poland"
        }
      },
      "projects": [
        {
          "description": "Successfully finished a cost saving project before required deadline. Firstly as a team member, then since 2012 as a team leader. The project was the migration over 30 major airlines between the legacy system (based on HP NonStop Kernel) to the current system. The project was very challenging due to multiple dependencies (Sabre's internal systems, customer's systems), no downtime requirement, big amount of user data (data of 30M+ passengers of airlines), pressure of time, little documentation of the legacy system and all of it's features."
        },
        {
          "description": "Developed a library for comparing XMLs. What makes this library different from the other libraries of this type is the possibility of comparing XMLs ignoring the sequence of the elements of the same type. This is very useful if the elements of the same type in an XML represent elements of a set, and the sequence of the elements returned by the system is irrelevant. I've narrowed the problem to an assignment problem and used one of bipartite graph algorithms to solve the root problem."
        },
        {
          "description": "Introduced multiple improvements like: automated configuration diffs run by Jenkins, a shared configuration to omit files duplicates, best practices developers meetings, an usage of a pre tested commit, a local SVN slave to speed up read only operations, a global Maven's parent POM for dependencies management and plugins management, an unified configuration API as an abstraction over a configuration source (file, DB, JMX), RESTful monitoring application giving possibility for QAs to test aspects which were not testable before."
        },
        {
          "description": "Developed a fully functional application which integrates traveler's Facebook account with a profile stored in Sabre's Customer Profiles. It was done during the HackDay 2013 contest. The application was written in a Clojure."
        },
        {
          "description": "Successfully developed within 24 hours a 'proof of concept' application for the HackDay 2012 contest. The idea of the project was to introduce the idea of social media to the world of aviation. The application was written in a Clojure which none of team members didn't know before the contest. The project won the audience award. As a followup of the contest the application has been presented to Sabre's marketing team and it occurred that one of the major Sabre's customer is interested in buying the application."
        }
      ],
      "start-date": "2011-07",
      "end-date": "2014-02",
      "skills": [
        {
          "name": "Java",
          "detailed-name": "Java 1.6",
          "usage-frequency": "day-to-day",
          "category": "language"
        },
        {
          "name": "Java",
          "detailed-name": "Java 1.7",
          "usage-frequency": "day-to-day",
          "start-date": "2013-09",
          "category": "language"
        },
        {
          "name": "Spring",
          "usage-frequency": "day-to-day",
          "category": "library"
        },
        {
          "name": "Hibernate",
          "usage-frequency": "day-to-day",
          "category": "library"
        },
        {
          "name": "XSLT",
          "usage-frequency": "often",
          "category": "library"
        },
        {
          "name": "Guava",
          "usage-frequency": "often",
          "category": "library"
        },
        {
          "name": "Maven",
          "usage-frequency": "day-to-day",
          "category": "tool"
        },
        {
          "name": "Apache Wicket",
          "usage-frequency": "often",
          "category": "library"
        },
        {
          "name": "AspectJ",
          "usage-frequency": "occasionally",
          "category": "library"
        },
        {
          "name": "JUnit",
          "usage-frequency": "day-to-day",
          "category": "library"
        },
        {
          "name": "Mockito",
          "usage-frequency": "day-to-day",
          "category": "library"
        },
        {
          "name": "Fest",
          "usage-frequency": "day-to-day",
          "category": "library"
        },
        {
          "name": "MySQL",
          "usage-frequency": "often",
          "category": "database"
        },
        {
          "name": "MyBatis",
          "usage-frequency": "often",
          "category": "library"
        },
        {
          "name": "Apache Camel",
          "usage-frequency": "often",
          "category": "library"
        },
        {
          "name": "XPath",
          "usage-frequency": "often",
          "category": "other"
        },
        {
          "name": "XML",
          "usage-frequency": "often",
          "category": "other"
        },
        {
          "name": "XML Schema",
          "usage-frequency": "often",
          "category": "other"
        },
        {
          "name": "Oracle",
          "usage-frequency": "often",
          "category": "database"
        },
        {
          "name": "Clojure",
          "usage-frequency": "day-to-day",
          "start-date": "2013-06",
          "end-date": "2013-07",
          "category": "language"
        }
      ]
    },
    {
      "positions": [
        {
          "title": "Java Developer"
        }
      ],
      "employment": "full-time",
      "company": {
        "name": "Sylogic",
        "industry": "Websites",
        "location": {
          "city": "Warszawa",
          "country": "Poland"
        }
      },
      "projects": [
        {
          "description": "I've been developing web applications for customers. I took part of whole process of creating application (gathering requirements, analysis, designing, developing and deployment)"
        }
      ],
      "start-date": "2010-06",
      "end-date": "2011-06",
      "skills": [
        {
          "name": "Java",
          "detailed-name": "Java 6",
          "usage-frequency": "day-to-day",
          "category": "language"
        },
        {
          "name": "Spring",
          "usage-frequency": "day-to-day",
          "category": "library"
        },
        {
          "name": "Hibernate",
          "usage-frequency": "day-to-day",
          "category": "library"
        },
        {
          "name": "JSF",
          "usage-frequency": "day-to-day",
          "category": "library"
        },
        {
          "name": "Maven",
          "usage-frequency": "day-to-day",
          "category": "tool"
        },
        {
          "name": "Apache Wicket",
          "start-date": "2010-07",
          "end-date": "2010-10",
          "usage-frequency": "day-to-day",
          "category": "library"
        },
        {
          "name": "Tiles",
          "usage-frequency": "often",
          "category": "library"
        },
        {
          "name": "Intellij IDEA",
          "usage-frequency": "day-to-day",
          "category": "tool"
        }
      ]
    },
    {
      "positions": [
        {
          "title": "Linux administrator"
        }
      ],
      "employment": "part-time",
      "company": {
        "name": "ConSol* Consulting & Solutions Software Poland",
        "industry": "CRM",
        "location": {
          "city": "Krakow",
          "country": "Poland"
        }
      },
      "projects": [
        {
          "description": "I've built and been maintaining infrastructure for a technology company which employed 30 developers."
        },
        {
          "description": "Developed income optimizer for hospitals. Successfully deployed at the hospital in Sucha Beskidzka."
        },
        {
          "description": "Researched and developed a 'proof of concept' application WebCTI - Asterisk / ConSol* CM in a single person R&D project."
        }
      ],
      "start-date": "2006-01",
      "end-date": "2009-07",
      "skills": [
        {
          "name": "Linux",
          "usage-frequency": "day-to-day",
          "category": "os"
        },
        {
          "name": "Bash",
          "usage-frequency": "often",
          "category": "language"
        },
        {
          "name": "awk",
          "usage-frequency": "occasionally",
          "category": "language"
        },
        {
          "name": "Java",
          "detailed-name": "Java 6",
          "start-date": "2008-09",
          "end-date": "2008-11",
          "usage-frequency": "day-to-day",
          "category": "language"
        },
        {
          "name": "Apache Wicket",
          "start-date": "2008-09",
          "end-date": "2008-11",
          "usage-frequency": "day-to-day",
          "category": "library"
        },
        {
          "name": "Spring",
          "start-date": "2008-09",
          "end-date": "2008-11",
          "usage-frequency": "day-to-day",
          "category": "library"
        },
        {
          "name": "Hibernate",
          "start-date": "2008-09",
          "end-date": "2008-11",
          "usage-frequency": "day-to-day",
          "category": "library"
        },
        {
          "name": "Maven",
          "start-date": "2008-09",
          "end-date": "2008-11",
          "usage-frequency": "day-to-day",
          "category": "tool"
        },
        {
          "name": "Intellij IDEA",
          "start-date": "2008-09",
          "end-date": "2008-11",
          "usage-frequency": "day-to-day",
          "category": "tool"
        }
      ]
    }
  ],
  "recommendations": [
    {
      "name": "Szymon Paluchowski",
      "date": "April 7, 2013",
      "recommendation": "Working with Łukasz is a real pleasure. Extreme attention to details, always willing to help others, very fast at providing reliable development results. His technical knowledge is very good, allowing to propose the best solutions for solving problems. He's one of the best developers I've met."
    },
    {
      "name": "Maciej Hamiga",
      "date": "January 6, 2013",
      "recommendation": "Łukasz has proven to be one of the most valuable team members, with his wide technical knowledge, willingness to learn and - especially - unbelievable attention to details. Łukasz always aimed for the complete, perfect solution to a problem - half-measures never satisfied him. I would gladly work with him again."
    }
  ],
  "learning": {
    "education": [
      {
        "school-name": "AGH University of Science and Technology in Cracow",
        "start-date": "2004",
        "end-date": "2009",
        "field-of-study": "Computer Science"
      }
    ],
    "conferences-trainings": [
      {
        "name": "Uncle Bob's Advanced TDD",
        "type": "course",
        "date": "2015",
        "duration": "3 days",
        "www": "https://skillsmatter.com/courses"
      },
      {
        "name": "GeeCon",
        "type": "conference",
        "date": "2014",
        "duration": "3 days",
        "www": "http://2014.geecon.org/"
      },
      {
        "name": "JDD",
        "type": "conference",
        "date": "2013",
        "duration": "2 days",
        "www": "http://13.jdd.org.pl/en/"
      },
      {
        "name": "Java Developers’ Day",
        "type": "conference",
        "date": "2008",
        "duration": "1 day",
        "www": "http://08.jdd.org.pl/lang-pref/en/"
      },
      {
        "name": "Java Developers’ Day",
        "type": "conference",
        "date": "2006",
        "duration": "1 day",
        "www": "http://06.jdd.org.pl/?lp_lang_view=en"
      }
    ],
    "other": "Currently learning Scala and Clojure."
  }
}
